yamlformat/__init__.py
yamlformat/validator.py
yamlformat/tests/__init__.py
yamlformat/tests/base_lib_test.py
yamlformat/tests/config_folder_lib_test.py
yamlformat/tests/entity_type_lib_test.py
yamlformat/tests/entity_type_manager_test.py
yamlformat/tests/external_file_lib_test.py
yamlformat/tests/field_lib_test.py
yamlformat/tests/findings_lib_test.py
yamlformat/tests/namespace_validator_test.py
yamlformat/tests/parse_config_lib_test.py
yamlformat/tests/presubmit_validate_types_lib_test.py
yamlformat/tests/state_lib_test.py
yamlformat/tests/subfield_lib_test.py
yamlformat/tests/unit_lib_test.py
yamlformat/validator/__init__.py
yamlformat/validator/base_lib.py
yamlformat/validator/config_folder_lib.py
yamlformat/validator/entity_type_lib.py
yamlformat/validator/entity_type_manager.py
yamlformat/validator/external_file_lib.py
yamlformat/validator/field_lib.py
yamlformat/validator/findings_lib.py
yamlformat/validator/namespace_validator.py
yamlformat/validator/parse_config_lib.py
yamlformat/validator/presubmit_validate_types_lib.py
yamlformat/validator/state_lib.py
yamlformat/validator/subfield_lib.py
yamlformat/validator/test_helpers_lib.py
yamlformat/validator/unit_lib.py
yamlformat/validator/validate_types.py
ideology_yaml_validator-0.0.1.dist-info/LICENSE.txt
ideology_yaml_validator-0.0.1.dist-info/METADATA
ideology_yaml_validator-0.0.1.dist-info/WHEEL
ideology_yaml_validator-0.0.1.dist-info/top_level.txt
ideology_yaml_validator-0.0.1.dist-info/RECORD
